xunit_wrapper/__init__.py
xunit_wrapper-0.9.dist-info/DESCRIPTION.rst
xunit_wrapper-0.9.dist-info/METADATA
xunit_wrapper-0.9.dist-info/RECORD
xunit_wrapper-0.9.dist-info/WHEEL
xunit_wrapper-0.9.dist-info/metadata.json
xunit_wrapper-0.9.dist-info/top_level.txt
