Metadata-Version: 2.0
Name: xunit-wrapper
Version: 0.9
Summary: Wrap python functions with a decorator to handle building XUnit reports
Home-page: https://github.com/TAMU-CPT/xunit-python-decorator
Author: E Rasche
Author-email: esr@tamu.edu
License: GPL-3.0
Platform: UNKNOWN
Classifier: Development Status :: 4 - Beta
Classifier: Operating System :: OS Independent
Classifier: Intended Audience :: Developers
Classifier: Environment :: Console
Classifier: License :: OSI Approved :: GNU General Public License v3 (GPLv3)
Classifier: Operating System :: OS Independent
Requires-Dist: junit-xml (==1.7)
